README.txt
setup.cfg
setup.py
collective/__init__.py
collective.js.showmore.egg-info/PKG-INFO
collective.js.showmore.egg-info/SOURCES.txt
collective.js.showmore.egg-info/dependency_links.txt
collective.js.showmore.egg-info/namespace_packages.txt
collective.js.showmore.egg-info/not-zip-safe
collective.js.showmore.egg-info/requires.txt
collective.js.showmore.egg-info/top_level.txt
collective/js/__init__.py
collective/js/showmore/__init__.py
collective/js/showmore/configure.zcml
collective/js/showmore/showmore.js
collective/js/showmore/tests/README.txt
collective/js/showmore/tests/index.html
collective/js/showmore/tests/jquery-dev.js
collective/js/showmore/tests/test_showmore.js
collective/js/showmore/tests/qunit/testrunner.js
collective/js/showmore/tests/qunit/testsuite.css
docs/HISTORY.txt