Metadata-Version: 1.0
Name: collective.js.showmore
Version: 1.0a4
Summary: JS add-on to show/hide parts of a page.
Home-page: http://pypi.python.org/pypi/collective.js.showmore/
Author: Godefroid Chapelle
Author-email: gotcha@jarn.com
License: GPL
Keywords: javascript ajax jquery expansion expand markup
Platform: Any
Classifier: Development Status :: 3 - Alpha
Classifier: Environment :: Web Environment
Classifier: License :: OSI Approved :: GNU General Public License (GPL)
Classifier: Operating System :: OS Independent
Classifier: Programming Language :: Python
Classifier: Topic :: Software Development :: Libraries :: Python Modules
